it_depends/__init__.py
it_depends/__main__.py
it_depends/audit.py
it_depends/autotools.py
it_depends/cargo.py
it_depends/cli.py
it_depends/cmake.py
it_depends/db.py
it_depends/dependencies.py
it_depends/docker.py
it_depends/go.py
it_depends/graphs.py
it_depends/html.py
it_depends/it_depends.py
it_depends/native.py
it_depends/npm.py
it_depends/pip.py
it_depends/sbom.py
it_depends/vcs.py
it_depends/ubuntu/__init__.py
it_depends/ubuntu/apt.py
it_depends/ubuntu/docker.py
it_depends/ubuntu/resolver.py
it_depends-0.1.2.dist-info/LICENSE
it_depends-0.1.2.dist-info/METADATA
it_depends-0.1.2.dist-info/WHEEL
it_depends-0.1.2.dist-info/entry_points.txt
it_depends-0.1.2.dist-info/top_level.txt
it_depends-0.1.2.dist-info/RECORD
