Metadata-Version: 2.1
Name: it-depends
Version: 0.1.2
Summary: A software dependency analyzer
Home-page: https://github.com/trailofbits/it-depends
Author: Trail of Bits
License: LGPL-3.0-or-later
Classifier: Development Status :: 4 - Beta
Classifier: Environment :: Console
Classifier: Intended Audience :: Science/Research
Classifier: License :: OSI Approved :: GNU Lesser General Public License v3 or later (LGPLv3+)
Classifier: Programming Language :: Python :: 3 :: Only
Classifier: Topic :: Utilities
Requires-Python: >=3.7
License-File: LICENSE
Requires-Dist: appdirs>=1.4.4
Requires-Dist: cyclonedx-python-lib<9,>=5
Requires-Dist: docker>=4.4.0
Requires-Dist: graphviz>=0.14.1
Requires-Dist: johnnydep>=1.8
Requires-Dist: networkx>=2.4
Requires-Dist: parse_cmake>=0.4.1
Requires-Dist: semantic_version~=2.8.5
Requires-Dist: sqlalchemy>=1.3
Requires-Dist: tqdm>=4.48.0
Requires-Dist: requests>=2.20.0
Requires-Dist: urllib3>=1.26.5
Provides-Extra: dev
Requires-Dist: flake8; extra == "dev"
Requires-Dist: pytest; extra == "dev"
Requires-Dist: twine; extra == "dev"
Requires-Dist: mypy>=0.812; extra == "dev"
Requires-Dist: types-setuptools; extra == "dev"
Requires-Dist: types-requests; extra == "dev"
